Workbook

Sheet 投放明细表
A1: 基础信息 | G1: 内容信息 | I1: 费用数据 | P1: 效率指标
A2: 投放日期 | B2: 所属周 | C2: 平台 | D2: 达人ID | E2: 达人姓名 | F2: 内容链接 | G2: 款式编号 | H2: 内容类型 | I2: 达人合作费 | J2: 平台投放费 | K2: 样品/运费成本 | L2: 点击量 | M2: 点赞数 | N2: 收藏数 | O2: 评论数 | P2: 总互动量 | Q2: 互动率 | R2: 单互动成本
A3: 2026-01-01 | B3: 1周 | C3: 抖音 | F3: https://v.douyin.com/iAq4s_v7QHs/ | G3: 000A1 | H3: 文严文 | K3: 107.5 | L3: 7172 | M3: 395 | N3: 31 | O3: 16 | P3: =IF(AND(M3<>"",M3>0),M3+N3+O3,"") | Q3: =IF(AND(L3<>"",L3>0,P3<>""),P3/L3,"") | R3: =IF(AND(P3<>"",P3>0),(I3+J3+K3)/P3,"")
A4: 2026-01-01 | B4: 1周 | C4: 抖音 | F4: https://v.douyin.com/MSVmmfdkbVo/ | G4: 0001A1 | H4: 文严文 | K4: 107.5 | L4: 13000 | M4: 1051 | N4: 31 | O4: 43 | P4: =IF(AND(M4<>"",M4>0),M4+N4+O4,"") | Q4: =IF(AND(L4<>"",L4>0,P4<>""),P4/L4,"") | R4: =IF(AND(P4<>"",P4>0),(I4+J4+K4)/P4,"")
A5: 2026-01-01 | B5: 1周 | C5: 抖音 | F5: https://v.douyin.com/y3HUBilSJ-o/ | G5: 0001A1 | H5: 文严文 | K5: 107.5 | L5: 2500 | M5: 182 | N5: 5 | O5: 7 | P5: =IF(AND(M5<>"",M5>0),M5+N5+O5,"") | Q5: =IF(AND(L5<>"",L5>0,P5<>""),P5/L5,"") | R5: =IF(AND(P5<>"",P5>0),(I5+J5+K5)/P5,"")
A6: 2026-01-01 | B6: 1周 | C6: 抖音 | F6: https://v.douyin.com/sBAtJ5NSdU4/ | G6: 0001A1 | H6: 文严文 | K6: 107.5 | L6: 495 | M6: 39 | N6: 7 | O6: 6 | P6: =IF(AND(M6<>"",M6>0),M6+N6+O6,"") | Q6: =IF(AND(L6<>"",L6>0,P6<>""),P6/L6,"") | R6: =IF(AND(P6<>"",P6>0),(I6+J6+K6)/P6,"")
A7: 2026-01-01 | B7: 1周 | C7: 抖音 | F7: https://v.douyin.com/PbZ_SSzunx4/ | G7: 0001A1 | H7: 文严文 | K7: 107.5 | L7: 20000 | M7: 801 | N7: 55 | O7: 27 | P7: =IF(AND(M7<>"",M7>0),M7+N7+O7,"") | Q7: =IF(AND(L7<>"",L7>0,P7<>""),P7/L7,"") | R7: =IF(AND(P7<>"",P7>0),(I7+J7+K7)/P7,"")
A8: 2026-01-01 | B8: 1周 | C8: 抖音 | F8: https://v.douyin.com/YqtYSfjlS3E/ | G8: 0001A1 | H8: 文严文 | K8: 107.5 | L8: 500 | M8: 20 | N8: 1 | O8: 9 | P8: =IF(AND(M8<>"",M8>0),M8+N8+O8,"") | Q8: =IF(AND(L8<>"",L8>0,P8<>""),P8/L8,"") | R8: =IF(AND(P8<>"",P8>0),(I8+J8+K8)/P8,"")
A9: 2026-01-01 | B9: 1周 | C9: 抖音 | F9: https://v.douyin.com/-7BMiMRloiA/ | G9: 0001A1 | H9: 文严文 | K9: 107.5 | L9: 1500 | M9: 135 | N9: 5 | O9: 3 | P9: =IF(AND(M9<>"",M9>0),M9+N9+O9,"") | Q9: =IF(AND(L9<>"",L9>0,P9<>""),P9/L9,"") | R9: =IF(AND(P9<>"",P9>0),(I9+J9+K9)/P9,"")
A10: 2026-01-02 | B10: 1周 | C10: 抖音 | F10: https://v.douyin.com/_ZlCoCmlQak/ | G10: 0001A1 | H10: 文严文 | K10: 107.5 | L10: 1000 | M10: 154 | N10: 1 | O10: 18 | P10: =IF(AND(M10<>"",M10>0),M10+N10+O10,"") | Q10: =IF(AND(L10<>"",L10>0,P10<>""),P10/L10,"") | R10: =IF(AND(P10<>"",P10>0),(I10+J10+K10)/P10,"")
A11: 2026-01-02 | B11: 1周 | C11: 抖音 | F11: https://v.douyin.com/V8o0WChiMZI/ | G11: 0001A1 | H11: 文严文 | K11: 107.5 | L11: 1000 | M11: 63 | N11: 4 | O11: 5 | P11: =IF(AND(M11<>"",M11>0),M11+N11+O11,"") | Q11: =IF(AND(L11<>"",L11>0,P11<>""),P11/L11,"") | R11: =IF(AND(P11<>"",P11>0),(I11+J11+K11)/P11,"")
A12: 2026-01-02 | B12: 1周 | C12: 抖音 | F12: https://v.douyin.com/-bqQANPJZgo/ | G12: 1217W | H12: 杨博文 | K12: 54 | L12: 3950 | M12: 56 | N12: 0 | O12: 16 | P12: =IF(AND(M12<>"",M12>0),M12+N12+O12,"") | Q12: =IF(AND(L12<>"",L12>0,P12<>""),P12/L12,"") | R12: =IF(AND(P12<>"",P12>0),(I12+J12+K12)/P12,"")
A13: 2026-01-02 | B13: 1周 | C13: 抖音 | F13: https://v.douyin.com/BV1jlAeIbuY/ | G13: 0001A1 | H13: 文严文 | K13: 107.5 | L13: 1275 | M13: 172 | N13: 2 | O13: 30 | P13: =IF(AND(M13<>"",M13>0),M13+N13+O13,"") | Q13: =IF(AND(L13<>"",L13>0,P13<>""),P13/L13,"") | R13: =IF(AND(P13<>"",P13>0),(I13+J13+K13)/P13,"")
A14: 2026-01-02 | B14: 1周 | C14: 抖音 | F14: https://v.douyin.com/iUlPRxVKQeU/ | G14: 495 | H14: 口播 | I14: 1000 | K14: 93 | L14: 303000 | M14: 13000 | N14: 1079 | O14: 124 | P14: =IF(AND(M14<>"",M14>0),M14+N14+O14,"") | Q14: =IF(AND(L14<>"",L14>0,P14<>""),P14/L14,"") | R14: =IF(AND(P14<>"",P14>0),(I14+J14+K14)/P14,"")
A15: 2026-01-02 | B15: 1周 | C15: 小红书 | F15: https://www.xiaohongshu.com/discovery/item/6957ad6c000000001e02382a?xsec_token=CB7z5rQCX629KondpFe6PuhJqLRd1NAcs3xKxQq6bKlzk=&xsec_source=app_share&type=video | G15: 495 | H15: 口播 | I15: 300 | K15: 93 | L15: 4364 | M15: 361 | N15: 189 | O15: 32 | P15: =IF(AND(M15<>"",M15>0),M15+N15+O15,"") | Q15: =IF(AND(L15<>"",L15>0,P15<>""),P15/L15,"") | R15: =IF(AND(P15<>"",P15>0),(I15+J15+K15)/P15,"")
A16: 2026-01-02 | B16: 1周 | C16: 小红书 | F16: https://www.xiaohongshu.com/discovery/item/6957c123000000001e02c96d?xsec_token=CBrSeaQKI4NDONmRGzS_ay9M7Y0vylVCzbmfkYZlmIL20=&xsec_source=app_share | G16: 495 | H16: 穿搭 | I16: 120 | K16: 93 | L16: 3759 | M16: 436 | N16: 117 | O16: 13 | P16: =IF(AND(M16<>"",M16>0),M16+N16+O16,"") | Q16: =IF(AND(L16<>"",L16>0,P16<>""),P16/L16,"") | R16: =IF(AND(P16<>"",P16>0),(I16+J16+K16)/P16,"")
A17: 2026-01-02 | B17: 1周 | C17: 小红书 | F17: https://www.xiaohongshu.com/discovery/item/6957d5e6000000002103fa96?xsec_token=CBYfSKHbvyxrrScDjtB8lffVUagleEJuvM8nGcParZ29w=&xsec_source=app_share&type=video | G17: 1217W | H17: 杨博文 | K17: 54 | L17: 158 | M17: 14 | N17: 3 | O17: 0 | P17: =IF(AND(M17<>"",M17>0),M17+N17+O17,"") | Q17: =IF(AND(L17<>"",L17>0,P17<>""),P17/L17,"") | R17: =IF(AND(P17<>"",P17>0),(I17+J17+K17)/P17,"")
A18: 2026-01-03 | B18: 1周 | C18: 抖音 | F18: https://v.douyin.com/SkcssLfRA0A/ | G18: 0001A1 | H18: 文严文 | K18: 107.5 | L18: 602 | M18: 26 | N18: 3 | O18: 19 | P18: =IF(AND(M18<>"",M18>0),M18+N18+O18,"") | Q18: =IF(AND(L18<>"",L18>0,P18<>""),P18/L18,"") | R18: =IF(AND(P18<>"",P18>0),(I18+J18+K18)/P18,"")
A19: 2026-01-03 | B19: 1周 | C19: 抖音 | F19: https://v.douyin.com/IzJdX82p4mw/ | G19: 493AX | H19: 穿搭 | K19: 98 | L19: 1831 | M19: 134 | N19: 3 | O19: 11 | P19: =IF(AND(M19<>"",M19>0),M19+N19+O19,"") | Q19: =IF(AND(L19<>"",L19>0,P19<>""),P19/L19,"") | R19: =IF(AND(P19<>"",P19>0),(I19+J19+K19)/P19,"")
A20: 2026-01-03 | B20: 1周 | C20: 抖音 | F20: https://v.douyin.com/rUAcExNJkKQ/ | G20: 0001A1 | H20: 新年好物 | K20: 107.5 | L20: 13000 | M20: 291 | N20: 77 | O20: 15 | P20: =IF(AND(M20<>"",M20>0),M20+N20+O20,"") | Q20: =IF(AND(L20<>"",L20>0,P20<>""),P20/L20,"") | R20: =IF(AND(P20<>"",P20>0),(I20+J20+K20)/P20,"")
A21: 2026-01-03 | B21: 1周 | C21: 抖音 | F21: https://v.douyin.com/cJTvVLIzgLw/ | G21: 493AX | H21: 穿搭 | K21: 98 | L21: 1000 | M21: 50 | N21: 2 | O21: 10 | P21: =IF(AND(M21<>"",M21>0),M21+N21+O21,"") | Q21: =IF(AND(L21<>"",L21>0,P21<>""),P21/L21,"") | R21: =IF(AND(P21<>"",P21>0),(I21+J21+K21)/P21,"")
A22: 2026-01-03 | B22: 1周 | C22: 抖音 | F22: https://v.douyin.com/lYBNGlgl0NU/ | G22: 0001A1 | H22: 文严文 | K22: 107.5 | L22: 2333 | M22: 354 | N22: 10 | O22: 40 | P22: =IF(AND(M22<>"",M22>0),M22+N22+O22,"") | Q22: =IF(AND(L22<>"",L22>0,P22<>""),P22/L22,"") | R22: =IF(AND(P22<>"",P22>0),(I22+J22+K22)/P22,"")
A23: 2026-01-03 | B23: 1周 | C23: 抖音 | F23: https://v.douyin.com/4CBvLPGC0ZI/ | G23: 495 | H23: 新年好物 | I23: 300 | K23: 93 | L23: 18000 | M23: 416 | N23: 167 | O23: 35 | P23: =IF(AND(M23<>"",M23>0),M23+N23+O23,"") | Q23: =IF(AND(L23<>"",L23>0,P23<>""),P23/L23,"") | R23: =IF(AND(P23<>"",P23>0),(I23+J23+K23)/P23,"")
A24: 2026-01-03 | B24: 1周 | C24: 抖音 | F24: https://v.douyin.com/osf5qWQPFkE/ | G24: 0001A1 | H24: 穿搭 | K24: 107.5 | L24: 14000 | M24: 924 | N24: 111 | O24: 19 | P24: =IF(AND(M24<>"",M24>0),M24+N24+O24,"") | Q24: =IF(AND(L24<>"",L24>0,P24<>""),P24/L24,"") | R24: =IF(AND(P24<>"",P24>0),(I24+J24+K24)/P24,"")
A25: 2026-01-03 | B25: 1周 | C25: 抖音 | F25: https://v.douyin.com/QJ8Yl1xI9cE/ | G25: 495 | H25: 穿搭 | I25: 20 | K25: 93 | L25: 9449 | M25: 296 | N25: 27 | O25: 27 | P25: =IF(AND(M25<>"",M25>0),M25+N25+O25,"") | Q25: =IF(AND(L25<>"",L25>0,P25<>""),P25/L25,"") | R25: =IF(AND(P25<>"",P25>0),(I25+J25+K25)/P25,"")
A26: 2026-01-03 | B26: 1周 | C26: 抖音 | F26: https://v.douyin.com/xoDXL9GJD0k/ | G26: 0001A1 | H26: 文严文 | K26: 107.5 | L26: 5102 | M26: 1022 | N26: 10 | O26: 29 | P26: =IF(AND(M26<>"",M26>0),M26+N26+O26,"") | Q26: =IF(AND(L26<>"",L26>0,P26<>""),P26/L26,"") | R26: =IF(AND(P26<>"",P26>0),(I26+J26+K26)/P26,"")
A27: 2026-01-03 | B27: 1周 | C27: 抖音 | F27: https://v.douyin.com/2YJ15N_BR-s/ | G27: 0001A1 | H27: 穿搭 | I27: 150 | K27: 107.5 | L27: 11000 | M27: 1035 | N27: 59 | O27: 21 | P27: =IF(AND(M27<>"",M27>0),M27+N27+O27,"") | Q27: =IF(AND(L27<>"",L27>0,P27<>""),P27/L27,"") | R27: =IF(AND(P27<>"",P27>0),(I27+J27+K27)/P27,"")
A28: 2026-01-03 | B28: 1周 | C28: 抖音 | F28: https://v.douyin.com/XslTSsTit24/ | G28: 0001A1 | H28: 文严文 | K28: 107.5 | L28: 1280 | M28: 101 | N28: 2 | O28: 11 | P28: =IF(AND(M28<>"",M28>0),M28+N28+O28,"") | Q28: =IF(AND(L28<>"",L28>0,P28<>""),P28/L28,"") | R28: =IF(AND(P28<>"",P28>0),(I28+J28+K28)/P28,"")
A29: 2026-01-03 | B29: 1周 | C29: 抖音 | F29: https://v.douyin.com/1PcAmW41d4I/ | G29: 495 | H29: 穿搭 | K29: 93 | L29: 95000 | M29: 2009 | N29: 518 | O29: 68 | P29: =IF(AND(M29<>"",M29>0),M29+N29+O29,"") | Q29: =IF(AND(L29<>"",L29>0,P29<>""),P29/L29,"") | R29: =IF(AND(P29<>"",P29>0),(I29+J29+K29)/P29,"")
A30: 2026-01-03 | B30: 1周 | C30: 抖音 | F30: https://v.douyin.com/OyKLbv7VQAI/ | G30: 489Y | H30: 赵露思 | K30: 53.5 | L30: 3000 | M30: 165 | N30: 4 | O30: 5 | P30: =IF(AND(M30<>"",M30>0),M30+N30+O30,"") | Q30: =IF(AND(L30<>"",L30>0,P30<>""),P30/L30,"") | R30: =IF(AND(P30<>"",P30>0),(I30+J30+K30)/P30,"")
A31: 2026-01-03 | B31: 1周 | C31: 抖音 | F31: https://v.douyin.com/z677vQz_ZX4/ | G31: 0001A1 | H31: 文严文 | K31: 107.5 | L31: 1912 | M31: 142 | N31: 9 | O31: 10 | P31: =IF(AND(M31<>"",M31>0),M31+N31+O31,"") | Q31: =IF(AND(L31<>"",L31>0,P31<>""),P31/L31,"") | R31: =IF(AND(P31<>"",P31>0),(I31+J31+K31)/P31,"")
A32: 2026-01-03 | B32: 1周 | C32: 小红书 | F32: https://www.xiaohongshu.com/discovery/item/69585a75000000001e00544f?xsec_token=CBDgYDsKpY4fARgqZp-CQn40MEd2uZhBGh8Zxc_ojwweU=&xsec_source=app_share&type=video | G32: 495 | H32: 口播 | I32: 250 | K32: 93 | L32: 17108 | M32: 1177 | N32: 428 | O32: 26 | P32: =IF(AND(M32<>"",M32>0),M32+N32+O32,"") | Q32: =IF(AND(L32<>"",L32>0,P32<>""),P32/L32,"") | R32: =IF(AND(P32<>"",P32>0),(I32+J32+K32)/P32,"")
A33: 2026-01-03 | B33: 1周 | C33: 小红书 | F33: https://www.xiaohongshu.com/discovery/item/6958fd95000000001d03bb46?xsec_token=CBtI3pB-Y_0lIL19kT25cWxtvSJknDiuoJq1gp6CUV4Vc=&xsec_source=app_share&type=video | G33: 0001A1 | H33: 穿搭 | I33: 300 | K33: 107.5 | L33: 15249 | M33: 1281 | N33: 664 | O33: 27 | P33: =IF(AND(M33<>"",M33>0),M33+N33+O33,"") | Q33: =IF(AND(L33<>"",L33>0,P33<>""),P33/L33,"") | R33: =IF(AND(P33<>"",P33>0),(I33+J33+K33)/P33,"")
A34: 2026-01-04 | B34: 1周 | C34: 抖音 | F34: https://v.douyin.com/rggb7eesuWU/ | G34: 495 | H34: 穿搭 | I34: 100 | K34: 93 | L34: 28000 | M34: 1952 | N34: 342 | O34: 44 | P34: =IF(AND(M34<>"",M34>0),M34+N34+O34,"") | Q34: =IF(AND(L34<>"",L34>0,P34<>""),P34/L34,"") | R34: =IF(AND(P34<>"",P34>0),(I34+J34+K34)/P34,"")
A35: 2026-01-04 | B35: 1周 | C35: 抖音 | F35: https://v.douyin.com/WpHk0afBuOs/ | G35: 0001A1 | H35: 穿搭 | K35: 107.5 | L35: 7000 | M35: 170 | N35: 5 | O35: 40 | P35: =IF(AND(M35<>"",M35>0),M35+N35+O35,"") | Q35: =IF(AND(L35<>"",L35>0,P35<>""),P35/L35,"") | R35: =IF(AND(P35<>"",P35>0),(I35+J35+K35)/P35,"")
A36: 2026-01-04 | B36: 1周 | C36: 抖音 | F36: https://v.douyin.com/r0Kr4KyY2OE/ | G36: 495 | H36: 穿搭 | K36: 93 | L36: 17000 | M36: 1140 | N36: 100 | O36: 153 | P36: =IF(AND(M36<>"",M36>0),M36+N36+O36,"") | Q36: =IF(AND(L36<>"",L36>0,P36<>""),P36/L36,"") | R36: =IF(AND(P36<>"",P36>0),(I36+J36+K36)/P36,"")
A37: 2026-01-04 | B37: 1周 | C37: 抖音 | F37: https://v.douyin.com/T5g_YI_-xSw/ | G37: 0001A1 | H37: 穿搭 | K37: 107.5 | L37: 3973 | M37: 188 | N37: 57 | O37: 3 | P37: =IF(AND(M37<>"",M37>0),M37+N37+O37,"") | Q37: =IF(AND(L37<>"",L37>0,P37<>""),P37/L37,"") | R37: =IF(AND(P37<>"",P37>0),(I37+J37+K37)/P37,"")
A38: 2026-01-04 | B38: 1周 | C38: 抖音 | F38: https://v.douyin.com/mmBK772VbHE/ | G38: 495 | H38: 程相 | K38: 93 | L38: 2193 | M38: 34 | N38: 1 | O38: 4 | P38: =IF(AND(M38<>"",M38>0),M38+N38+O38,"") | Q38: =IF(AND(L38<>"",L38>0,P38<>""),P38/L38,"") | R38: =IF(AND(P38<>"",P38>0),(I38+J38+K38)/P38,"")
A39: 2026-01-04 | B39: 1周 | C39: 小红书 | F39: https://www.xiaohongshu.com/discovery/item/6959cc78000000001e02a003?xsec_token=CBg5TFQuZ372BLFvhRJZYNwrMeYGh5FRSZUpHfXASYbL0=&xsec_source=app_share | G39: 489Y | H39: 赵露思 | K39: 53.5 | L39: 1132 | M39: 105 | N39: 8 | O39: 4 | P39: =IF(AND(M39<>"",M39>0),M39+N39+O39,"") | Q39: =IF(AND(L39<>"",L39>0,P39<>""),P39/L39,"") | R39: =IF(AND(P39<>"",P39>0),(I39+J39+K39)/P39,"")
A40: 2026-01-04 | B40: 1周 | C40: 小红书 | F40: https://www.xiaohongshu.com/discovery/item/6959d71b000000001e03669f?xsec_token=CBimvAsSiO23cNWAhp8h_RL7bp4cWaOwmqBaLS1l4mZZQ=&xsec_source=app_share | G40: 0001A1 | H40: 穿搭 | K40: 107.5 | L40: 2550 | M40: 149 | N40: 59 | O40: 16 | P40: =IF(AND(M40<>"",M40>0),M40+N40+O40,"") | Q40: =IF(AND(L40<>"",L40>0,P40<>""),P40/L40,"") | R40: =IF(AND(P40<>"",P40>0),(I40+J40+K40)/P40,"")
A41: 2026-01-04 | B41: 1周 | C41: 小红书 | F41: https://www.xiaohongshu.com/discovery/item/695a353b0000000022020036?xsec_token=CB61n2IJwtZjFw25pAO5v82wQKswHzOz9lPxH1pMqRH_I=&xsec_source=app_share&type=video | G41: 495 | H41: 口播 | I41: 200 | K41: 93 | L41: 32411 | M41: 1409 | N41: 489 | O41: 93 | P41: =IF(AND(M41<>"",M41>0),M41+N41+O41,"") | Q41: =IF(AND(L41<>"",L41>0,P41<>""),P41/L41,"") | R41: =IF(AND(P41<>"",P41>0),(I41+J41+K41)/P41,"")
A42: 2026-01-04 | B42: 1周 | C42: 小红书 | F42: https://www.xiaohongshu.com/discovery/item/695a4103000000002103c141?xsec_token=CBpJKWCa8ijW8ezU7OOP1jVsw_uthuTOR-AIrLpnzZtJY=&xsec_source=app_share&type=video | G42: 0001A1 | H42: 口播 | K42: 107.5 | L42: 2330 | M42: 168 | N42: 50 | O42: 36 | P42: =IF(AND(M42<>"",M42>0),M42+N42+O42,"") | Q42: =IF(AND(L42<>"",L42>0,P42<>""),P42/L42,"") | R42: =IF(AND(P42<>"",P42>0),(I42+J42+K42)/P42,"")
A43: 2026-01-04 | B43: 1周 | C43: 小红书 | F43: https://www.xiaohongshu.com/discovery/item/695a46fd000000001d03a796?xsec_token=CB-vF4YG65AQG1jxBv8cWJ_28coPJKc2kz_-_FfuiYJL0=&xsec_source=app_share | G43: 0001A1 | H43: 文严文 | K43: 107.5 | L43: 1205 | M43: 74 | N43: 8 | O43: 16 | P43: =IF(AND(M43<>"",M43>0),M43+N43+O43,"") | Q43: =IF(AND(L43<>"",L43>0,P43<>""),P43/L43,"") | R43: =IF(AND(P43<>"",P43>0),(I43+J43+K43)/P43,"")
A44: 2026-01-04 | B44: 1周 | C44: 小红书 | F44: https://www.xiaohongshu.com/discovery/item/695a48f6000000001e022840?xsec_token=CB-vF4YG65AQG1jxBv8cWJ__ZFJzCp7i4x8d1Vc7h27BQ=&xsec_source=app_share | G44: 489Y | H44: 赵露思 | K44: 53.5 | L44: 100 | M44: 12 | N44: 1 | O44: 0 | P44: =IF(AND(M44<>"",M44>0),M44+N44+O44,"") | Q44: =IF(AND(L44<>"",L44>0,P44<>""),P44/L44,"") | R44: =IF(AND(P44<>"",P44>0),(I44+J44+K44)/P44,"")
A45: 2026-01-04 | B45: 1周 | C45: 小红书 | F45: https://www.xiaohongshu.com/discovery/item/695a739b000000001e010fc6?xsec_token=CB-vF4YG65AQG1jxBv8cWJ_wJHNbGq-X-jUtWGdlLeI04=&xsec_source=app_share&type=video | G45: 1227W | H45: 穿搭 | K45: 61 | L45: 11752 | M45: 1443 | N45: 462 | O45: 35 | P45: =IF(AND(M45<>"",M45>0),M45+N45+O45,"") | Q45: =IF(AND(L45<>"",L45>0,P45<>""),P45/L45,"") | R45: =IF(AND(P45<>"",P45>0),(I45+J45+K45)/P45,"")
A46: 2026-01-04 | B46: 1周 | C46: 小红书 | F46: https://www.xiaohongshu.com/discovery/item/695a7a40000000001e030c57?xsec_token=CBMiVFiTeHrGy3WeIgr3XxuPECxiVkur9SLxNCnUb5MXw=&xsec_source=app_share | G46: 0001A1 | H46: 文严文 | K46: 107.5 | L46: 168 | M46: 12 | N46: 2 | O46: 1 | P46: =IF(AND(M46<>"",M46>0),M46+N46+O46,"") | Q46: =IF(AND(L46<>"",L46>0,P46<>""),P46/L46,"") | R46: =IF(AND(P46<>"",P46>0),(I46+J46+K46)/P46,"")
A47: 2026-01-05 | B47: 2周 | C47: 抖音 | F47: https://v.douyin.com/qSZbest8TQM/ | G47: 495 | H47: 穿搭 | K47: 93 | L47: 44000 | M47: 819 | N47: 703 | O47: 31 | P47: =IF(AND(M47<>"",M47>0),M47+N47+O47,"") | Q47: =IF(AND(L47<>"",L47>0,P47<>""),P47/L47,"") | R47: =IF(AND(P47<>"",P47>0),(I47+J47+K47)/P47,"")
A48: 2026-01-05 | B48: 2周 | C48: 抖音 | F48: https://v.douyin.com/fLSe1oiujb0/ | G48: 495 | H48: 开箱 | K48: 93 | L48: 16000 | M48: 678 | N48: 293 | O48: 40 | P48: =IF(AND(M48<>"",M48>0),M48+N48+O48,"") | Q48: =IF(AND(L48<>"",L48>0,P48<>""),P48/L48,"") | R48: =IF(AND(P48<>"",P48>0),(I48+J48+K48)/P48,"")
A49: 2026-01-05 | B49: 2周 | C49: 视频号 | G49: 493AX | H49: 王一珩 | K49: 98 | L49: 30000 | M49: 1058 | N49: 349 | O49: 63 | P49: =IF(AND(M49<>"",M49>0),M49+N49+O49,"") | Q49: =IF(AND(L49<>"",L49>0,P49<>""),P49/L49,"") | R49: =IF(AND(P49<>"",P49>0),(I49+J49+K49)/P49,"")
A50: 2026-01-05 | B50: 2周 | C50: 抖音 | F50: https://v.douyin.com/ZEV9zKpvA0E/ | G50: 493AX | H50: 王一珩 | K50: 98 | L50: 205000 | M50: 7625 | N50: 688 | O50: 401 | P50: =IF(AND(M50<>"",M50>0),M50+N50+O50,"") | Q50: =IF(AND(L50<>"",L50>0,P50<>""),P50/L50,"") | R50: =IF(AND(P50<>"",P50>0),(I50+J50+K50)/P50,"")
A51: 2026-01-05 | B51: 2周 | C51: 抖音 | F51: https://v.douyin.com/Y2TqQTeBIdw/ | G51: 493AX | H51: 穿搭 | K51: 98 | L51: 9788 | M51: 243 | N51: 6 | O51: 17 | P51: =IF(AND(M51<>"",M51>0),M51+N51+O51,"") | Q51: =IF(AND(L51<>"",L51>0,P51<>""),P51/L51,"") | R51: =IF(AND(P51<>"",P51>0),(I51+J51+K51)/P51,"")
A52: 2026-01-05 | B52: 2周 | C52: 抖音 | F52: https://v.douyin.com/Hg65AnQNXVQ/ | G52: 495 | H52: 穿搭 | K52: 93 | L52: 10000 | M52: 255 | N52: 30 | O52: 218 | P52: =IF(AND(M52<>"",M52>0),M52+N52+O52,"") | Q52: =IF(AND(L52<>"",L52>0,P52<>""),P52/L52,"") | R52: =IF(AND(P52<>"",P52>0),(I52+J52+K52)/P52,"")
A53: 2026-01-05 | B53: 2周 | C53: b站 | F53: https://www.bilibili.com/video/BV1nci4BPEqv/?share_source=copy_web | G53: 495 | H53: 穿搭 | K53: 93 | L53: 419 | M53: 6 | N53: 4 | O53: 3 | P53: =IF(AND(M53<>"",M53>0),M53+N53+O53,"") | Q53: =IF(AND(L53<>"",L53>0,P53<>""),P53/L53,"") | R53: =IF(AND(P53<>"",P53>0),(I53+J53+K53)/P53,"")
A54: 2026-01-05 | B54: 2周 | C54: 得物 | F54: https://m.dewu.com/rn-activity/community-share?trendId=440984244&shareType=0&source=videoTrend&shareId=yZQ6vlk&shareChannel=1 | G54: 495 | H54: 穿搭 | K54: 93 | L54: 177 | M54: 3 | N54: 0 | O54: 0 | P54: =IF(AND(M54<>"",M54>0),M54+N54+O54,"") | Q54: =IF(AND(L54<>"",L54>0,P54<>""),P54/L54,"") | R54: =IF(AND(P54<>"",P54>0),(I54+J54+K54)/P54,"")
A55: 2026-01-05 | B55: 2周 | C55: 得物 | F55: https://m.dewu.com/rn-activity/community-share?trendId=441036801&shareType=0&source=picTrend&shareId=yZQ6vlk&shareChannel=1 | G55: 495 | H55: 穿搭 | K55: 93 | L55: 122 | M55: 2 | N55: 0 | O55: 0 | P55: =IF(AND(M55<>"",M55>0),M55+N55+O55,"") | Q55: =IF(AND(L55<>"",L55>0,P55<>""),P55/L55,"") | R55: =IF(AND(P55<>"",P55>0),(I55+J55+K55)/P55,"")
A56: 2026-01-05 | B56: 2周 | C56: 抖音 | F56: https://v.douyin.com/oglz57q2-t4/ | G56: 495 | H56: 穿搭 | I56: 80 | K56: 93 | L56: 21000 | M56: 2170 | N56: 134 | O56: 48 | P56: =IF(AND(M56<>"",M56>0),M56+N56+O56,"") | Q56: =IF(AND(L56<>"",L56>0,P56<>""),P56/L56,"") | R56: =IF(AND(P56<>"",P56>0),(I56+J56+K56)/P56,"")
A57: 2026-01-05 | B57: 2周 | C57: 抖音 | F57: https://v.douyin.com/-xJlGqr2tXo/ | G57: 495 | H57: 穿搭 | K57: 93 | L57: 9544 | M57: 166 | N57: 22 | O57: 5 | P57: =IF(AND(M57<>"",M57>0),M57+N57+O57,"") | Q57: =IF(AND(L57<>"",L57>0,P57<>""),P57/L57,"") | R57: =IF(AND(P57<>"",P57>0),(I57+J57+K57)/P57,"")
A58: 2026-01-05 | B58: 2周 | C58: 小红书 | F58: https://www.xiaohongshu.com/discovery/item/695b6366000000000e03d0d7?xsec_token=CB_5DSRLMSO90sNHP4X0IRKMexlqiksCYs0BKkEmFBcr0=&xsec_source=app_share&type=video | G58: 493AX | H58: 王一珩 | K58: 98 | L58: 204491 | M58: 11056 | N58: 1231 | O58: 401 | P58: =IF(AND(M58<>"",M58>0),M58+N58+O58,"") | Q58: =IF(AND(L58<>"",L58>0,P58<>""),P58/L58,"") | R58: =IF(AND(P58<>"",P58>0),(I58+J58+K58)/P58,"")
A59: 2026-01-05 | B59: 2周 | C59: 小红书 | F59: https://www.xiaohongshu.com/discovery/item/695b8e0e000000000a02cc3f?xsec_token=CB2Xeta36-aYjDSLG1mloYaJ8x7LnQ882mHmz7Etajehk=&xsec_source=app_share&type=video | G59: 495 | H59: 穿搭 | K59: 93 | L59: 199 | M59: 13 | N59: 8 | O59: 1 | P59: =IF(AND(M59<>"",M59>0),M59+N59+O59,"") | Q59: =IF(AND(L59<>"",L59>0,P59<>""),P59/L59,"") | R59: =IF(AND(P59<>"",P59>0),(I59+J59+K59)/P59,"")
A60: 2026-01-05 | B60: 2周 | C60: 小红书 | F60: https://www.xiaohongshu.com/discovery/item/695ba6e500000000210290c3?xsec_token=CBRAxOc8JfdLmzPqo5lIkhIGz2rskIYJxVLoMUt-PMHH4=&xsec_source=app_share&type=video | G60: 495 | H60: 穿搭 | K60: 93 | L60: 3635 | M60: 263 | N60: 17 | O60: 25 | P60: =IF(AND(M60<>"",M60>0),M60+N60+O60,"") | Q60: =IF(AND(L60<>"",L60>0,P60<>""),P60/L60,"") | R60: =IF(AND(P60<>"",P60>0),(I60+J60+K60)/P60,"")
A61: 2026-01-05 | B61: 2周 | C61: 小红书 | F61: https://www.xiaohongshu.com/discovery/item/695bce1c000000002200a899?xsec_token=CBSwxRrUAc4VjoIn3aUIZ0su0YcIlhAJbjgvvo-c-YNYM=&xsec_source=app_share | G61: 495 | H61: 高桥大翔 | K61: 93 | L61: 243 | M61: 9 | N61: 0 | O61: 6 | P61: =IF(AND(M61<>"",M61>0),M61+N61+O61,"") | Q61: =IF(AND(L61<>"",L61>0,P61<>""),P61/L61,"") | R61: =IF(AND(P61<>"",P61>0),(I61+J61+K61)/P61,"")
A62: 2026-01-06 | B62: 2周 | C62: 抖音 | F62: https://v.douyin.com/K77jhMhrcKI/ | G62: 495 | H62: 穿搭 | K62: 93 | L62: 16000 | M62: 391 | N62: 22 | O62: 20 | P62: =IF(AND(M62<>"",M62>0),M62+N62+O62,"") | Q62: =IF(AND(L62<>"",L62>0,P62<>""),P62/L62,"") | R62: =IF(AND(P62<>"",P62>0),(I62+J62+K62)/P62,"")
A63: 2026-01-06 | B63: 2周 | C63: 得物 | F63: https://v.douyin.com/bndrzFmE-2g/ | G63: 495 | H63: 穿搭 | I63: 100 | K63: 93 | L63: 19000 | M63: 300 | N63: 71 | O63: 27 | P63: =IF(AND(M63<>"",M63>0),M63+N63+O63,"") | Q63: =IF(AND(L63<>"",L63>0,P63<>""),P63/L63,"") | R63: =IF(AND(P63<>"",P63>0),(I63+J63+K63)/P63,"")
A64: 2026-01-06 | B64: 2周 | C64: 抖音 | F64: https://v.douyin.com/9piR5SAyY6w/ | G64: 495 | H64: 穿搭 | K64: 93 | L64: 34000 | M64: 4191 | N64: 252 | O64: 35 | P64: =IF(AND(M64<>"",M64>0),M64+N64+O64,"") | Q64: =IF(AND(L64<>"",L64>0,P64<>""),P64/L64,"") | R64: =IF(AND(P64<>"",P64>0),(I64+J64+K64)/P64,"")
A65: 2026-01-06 | B65: 2周 | C65: 小红书 | F65: https://www.xiaohongshu.com/discovery/item/695c7bea000000001a01c289?xsec_token=CBxTa2K_G9qNtzKEcIMrDmQ8GMKbHx5Rks5TMhm5Yjxqk=&xsec_source=app_share&type=video | G65: 495 | H65: 程相 | K65: 93 | L65: 201 | M65: 20 | N65: 0 | O65: 3 | P65: =IF(AND(M65<>"",M65>0),M65+N65+O65,"") | Q65: =IF(AND(L65<>"",L65>0,P65<>""),P65/L65,"") | R65: =IF(AND(P65<>"",P65>0),(I65+J65+K65)/P65,"")
A66: 2026-01-06 | B66: 2周 | C66: 小红书 | F66: https://www.xiaohongshu.com/discovery/item/695cd08e000000001a0358f9?xsec_token=CBNDpYQDmQOq_8M3LteoHIIw3zy2UVuFKExXRMvpxk7V4=&xsec_source=app_share&type=video | G66: 495 | H66: 口播 | I66: 80 | K66: 93 | L66: 5980 | M66: 691 | N66: 184 | O66: 43 | P66: =IF(AND(M66<>"",M66>0),M66+N66+O66,"") | Q66: =IF(AND(L66<>"",L66>0,P66<>""),P66/L66,"") | R66: =IF(AND(P66<>"",P66>0),(I66+J66+K66)/P66,"")
A67: 2026-01-07 | B67: 2周 | C67: 抖音 | F67: https://v.douyin.com/IHAIxEmtUqM/ | G67: 495 | H67: 穿搭 | K67: 93 | L67: 108000 | M67: 8029 | N67: 556 | O67: 87 | P67: =IF(AND(M67<>"",M67>0),M67+N67+O67,"") | Q67: =IF(AND(L67<>"",L67>0,P67<>""),P67/L67,"") | R67: =IF(AND(P67<>"",P67>0),(I67+J67+K67)/P67,"")
A68: 2026-01-07 | B68: 2周 | C68: 抖音 | F68: https://v.douyin.com/vUyOFA_2rfs/ | G68: 495 | H68: 穿搭 | K68: 93 | L68: 11000 | M68: 1658 | N68: 43 | O68: 22 | P68: =IF(AND(M68<>"",M68>0),M68+N68+O68,"") | Q68: =IF(AND(L68<>"",L68>0,P68<>""),P68/L68,"") | R68: =IF(AND(P68<>"",P68>0),(I68+J68+K68)/P68,"")
A69: 2026-01-07 | B69: 2周 | C69: 抖音 | F69: https://v.douyin.com/mzyL2vEwNok/ | G69: 495 | H69: 口播 | I69: 400 | K69: 93 | L69: 11000 | M69: 448 | N69: 8 | O69: 28 | P69: =IF(AND(M69<>"",M69>0),M69+N69+O69,"") | Q69: =IF(AND(L69<>"",L69>0,P69<>""),P69/L69,"") | R69: =IF(AND(P69<>"",P69>0),(I69+J69+K69)/P69,"")
A70: 2026-01-07 | B70: 2周 | C70: 抖音 | F70: https://v.douyin.com/bRA1WBdPjo4/ | G70: 495 | H70: 穿搭 | K70: 93 | L70: 8000 | M70: 722 | N70: 4 | O70: 1 | P70: =IF(AND(M70<>"",M70>0),M70+N70+O70,"") | Q70: =IF(AND(L70<>"",L70>0,P70<>""),P70/L70,"") | R70: =IF(AND(P70<>"",P70>0),(I70+J70+K70)/P70,"")
A71: 2026-01-07 | B71: 2周 | C71: 小红书 | F71: https://www.xiaohongshu.com/discovery/item/695dcfc8000000001a02c615?xsec_token=CB5Z-wvgIDzNTULzsZu4iWQkm37ED-CYtMNl74rXzZEno=&xsec_source=app_share | G71: 495 | H71: 穿搭 | K71: 93 | L71: 9779 | M71: 1482 | N71: 107 | O71: 27 | P71: =IF(AND(M71<>"",M71>0),M71+N71+O71,"") | Q71: =IF(AND(L71<>"",L71>0,P71<>""),P71/L71,"") | R71: =IF(AND(P71<>"",P71>0),(I71+J71+K71)/P71,"")
A72: 2026-01-07 | B72: 2周 | C72: 小红书 | F72: https://www.xiaohongshu.com/discovery/item/695e05d5000000002103292e?xsec_token=CBl3p62QBA5Vuh3ZUwNSoeqQbjXpAK1fKG7rJSRi3Kass=&xsec_source=app_share&type=video | G72: 495 | H72: 穿搭 | I72: 100 | K72: 93 | L72: 15008 | M72: 1014 | N72: 248 | O72: 34 | P72: =IF(AND(M72<>"",M72>0),M72+N72+O72,"") | Q72: =IF(AND(L72<>"",L72>0,P72<>""),P72/L72,"") | R72: =IF(AND(P72<>"",P72>0),(I72+J72+K72)/P72,"")
A73: 2026-01-08 | B73: 2周 | C73: 抖音 | F73: https://v.douyin.com/Gkl3t0HX1tQ/ | G73: 495 | H73: 穿搭 | K73: 93 | L73: 1268 | M73: 111 | N73: 9 | O73: 8 | P73: =IF(AND(M73<>"",M73>0),M73+N73+O73,"") | Q73: =IF(AND(L73<>"",L73>0,P73<>""),P73/L73,"") | R73: =IF(AND(P73<>"",P73>0),(I73+J73+K73)/P73,"")
A74: 2026-01-08 | B74: 2周 | C74: 抖音 | F74: https://v.douyin.com/MEHAtB3w8so/ | G74: 495 | H74: 好物分享 | K74: 93 | L74: 900 | M74: 15 | N74: 1 | O74: 0 | P74: =IF(AND(M74<>"",M74>0),M74+N74+O74,"") | Q74: =IF(AND(L74<>"",L74>0,P74<>""),P74/L74,"") | R74: =IF(AND(P74<>"",P74>0),(I74+J74+K74)/P74,"")
A75: 2026-01-08 | B75: 2周 | C75: 小红书 | F75: https://www.xiaohongshu.com/discovery/item/695f821b000000001a02027c?xsec_token=CBnjzSCtjZUxaNiDfBPVBC7VBeXCfb3lADEWOVsLG87Bg=&xsec_source=app_share | G75: 1225 | H75: 新年好物 | K75: 55.5 | L75: 1041 | M75: 25 | N75: 7 | O75: 5 | P75: =IF(AND(M75<>"",M75>0),M75+N75+O75,"") | Q75: =IF(AND(L75<>"",L75>0,P75<>""),P75/L75,"") | R75: =IF(AND(P75<>"",P75>0),(I75+J75+K75)/P75,"")
A76: 2026-01-08 | B76: 2周 | C76: 小红书 | F76: https://www.xiaohongshu.com/discovery/item/695f9cbe000000000a029a22?xsec_token=CBDCAtsIsVEM00efUdA6toSYRTlmH1H_FRPZw6E4Vz7Sg=&xsec_source=app_share&type=video | G76: 495 | H76: 好物分享 | K76: 93 | L76: 766 | M76: 98 | N76: 19 | O76: 7 | P76: =IF(AND(M76<>"",M76>0),M76+N76+O76,"") | Q76: =IF(AND(L76<>"",L76>0,P76<>""),P76/L76,"") | R76: =IF(AND(P76<>"",P76>0),(I76+J76+K76)/P76,"")
A77: 2026-01-08 | B77: 2周 | C77: 小红书 | F77: https://www.xiaohongshu.com/discovery/item/695ddf2d000000000a0309e7?xsec_token=CBrJlAX0zfRCX1k9A9LE78DHyXZiBToyCapkEkdoqK8-I=&xsec_source=app_share&type=video | G77: 0001A1 | H77: 口播 | K77: 107.5 | L77: 9177 | M77: 374 | N77: 79 | O77: 25 | P77: =IF(AND(M77<>"",M77>0),M77+N77+O77,"") | Q77: =IF(AND(L77<>"",L77>0,P77<>""),P77/L77,"") | R77: =IF(AND(P77<>"",P77>0),(I77+J77+K77)/P77,"")
A78: 2026-01-08 | B78: 2周 | C78: 小红书 | F78: https://www.xiaohongshu.com/discovery/item/695fb3cc00000000220094d6?xsec_token=CBfuf0GwJ8D1wwfzsfS29jw09Fa-_wa5ZbsoseTPBya4s=&xsec_source=app_share&type=video | G78: 0001A1 | H78: 新年好物 | I78: 200 | K78: 107.5 | L78: 101077 | M78: 5452 | N78: 1741 | O78: 36 | P78: =IF(AND(M78<>"",M78>0),M78+N78+O78,"") | Q78: =IF(AND(L78<>"",L78>0,P78<>""),P78/L78,"") | R78: =IF(AND(P78<>"",P78>0),(I78+J78+K78)/P78,"")
A79: 2026-01-09 | B79: 2周 | C79: bilibili | F79: https://b23.tv/opPYYZr | G79: 495 | H79: 好物分享 | K79: 93 | L79: 9242 | M79: 713 | N79: 835 | O79: 6 | P79: =IF(AND(M79<>"",M79>0),M79+N79+O79,"") | Q79: =IF(AND(L79<>"",L79>0,P79<>""),P79/L79,"") | R79: =IF(AND(P79<>"",P79>0),(I79+J79+K79)/P79,"")
A80: 2026-01-09 | B80: 2周 | C80: 抖音 | F80: https://v.douyin.com/Isix0CnHE14/ | G80: 0001A1 | H80: 文严文 | K80: 107.5 | L80: 9185 | M80: 1205 | N80: 44 | O80: 25 | P80: =IF(AND(M80<>"",M80>0),M80+N80+O80,"") | Q80: =IF(AND(L80<>"",L80>0,P80<>""),P80/L80,"") | R80: =IF(AND(P80<>"",P80>0),(I80+J80+K80)/P80,"")
A81: 2026-01-09 | B81: 2周 | C81: 抖音 | F81: https://v.douyin.com/3anBUVPLECw/ | G81: 489Y | H81: 赵露思 | K81: 53.5 | L81: 2625 | M81: 182 | N81: 5 | O81: 8 | P81: =IF(AND(M81<>"",M81>0),M81+N81+O81,"") | Q81: =IF(AND(L81<>"",L81>0,P81<>""),P81/L81,"") | R81: =IF(AND(P81<>"",P81>0),(I81+J81+K81)/P81,"")
A82: 2026-01-09 | B82: 2周 | C82: 抖音 | F82: https://v.douyin.com/5er2OlcWLmU/ | G82: 0001A1 | H82: 新年好物 | K82: 107.5 | L82: 11000 | M82: 1104 | N82: 32 | O82: 13 | P82: =IF(AND(M82<>"",M82>0),M82+N82+O82,"") | Q82: =IF(AND(L82<>"",L82>0,P82<>""),P82/L82,"") | R82: =IF(AND(P82<>"",P82>0),(I82+J82+K82)/P82,"")
A83: 2026-01-09 | B83: 2周 | C83: 小红书 | F83: https://www.xiaohongshu.com/discovery/item/695ff9f8000000000a02c709?xsec_token=CBMQp-_bPQygpnLYIkeMtSwqD_nrkO3Ofm7EiVwoizPaA=&xsec_source=app_share&type=video | G83: 0001A1 | H83: 口播 | I83: 200 | K83: 107.5 | L83: 6913 | M83: 197 | N83: 83 | O83: 33 | P83: =IF(AND(M83<>"",M83>0),M83+N83+O83,"") | Q83: =IF(AND(L83<>"",L83>0,P83<>""),P83/L83,"") | R83: =IF(AND(P83<>"",P83>0),(I83+J83+K83)/P83,"")
A84: 2026-01-09 | B84: 2周 | C84: 小红书 | F84: https://www.xiaohongshu.com/discovery/item/6960cd6a0000000021030426?xsec_token=CBrtjIooTdO1vzsK6B5pKdGpstnagF80JmldLt4g3pZF8=&xsec_source=app_share&type=video | G84: 0001A1 | H84: 新年好物 | I84: 160 | K84: 107.5 | L84: 930 | M84: 185 | N84: 42 | O84: 15 | P84: =IF(AND(M84<>"",M84>0),M84+N84+O84,"") | Q84: =IF(AND(L84<>"",L84>0,P84<>""),P84/L84,"") | R84: =IF(AND(P84<>"",P84>0),(I84+J84+K84)/P84,"")
A85: 2026-01-09 | B85: 2周 | C85: 小红书 | F85: https://www.xiaohongshu.com/discovery/item/6960db01000000001a01ebac?xsec_token=CB0SFGO9pis6r9ufRVkv9ZJiKUM0n-cjZwGrHtXZnjSfc=&xsec_source=app_share&type=video | G85: 495 | H85: 穿搭 | I85: 200 | K85: 93 | L85: 30147 | M85: 2557 | N85: 961 | O85: 55 | P85: =IF(AND(M85<>"",M85>0),M85+N85+O85,"") | Q85: =IF(AND(L85<>"",L85>0,P85<>""),P85/L85,"") | R85: =IF(AND(P85<>"",P85>0),(I85+J85+K85)/P85,"")
A86: 2026-01-09 | B86: 2周 | C86: 小红书 | F86: https://www.xiaohongshu.com/discovery/item/6960ed220000000021030b02?xsec_token=CB7uHKffN68ZBi_gl8oTgYS3I57A_dgyjzL1cESW85XRc=&xsec_source=app_share&type=video | G86: 495 | H86: 口播 | I86: 400 | K86: 93 | L86: 271 | M86: 141 | N86: 79 | O86: 25 | P86: =IF(AND(M86<>"",M86>0),M86+N86+O86,"") | Q86: =IF(AND(L86<>"",L86>0,P86<>""),P86/L86,"") | R86: =IF(AND(P86<>"",P86>0),(I86+J86+K86)/P86,"")
A87: 2026-01-10 | B87: 2周 | C87: 抖音 | F87: https://v.douyin.com/hw2oNvQTrHc/ | G87: 495 | H87: 高桥大翔 | K87: 93 | L87: 3666 | M87: 185 | N87: 8 | O87: 23 | P87: =IF(AND(M87<>"",M87>0),M87+N87+O87,"") | Q87: =IF(AND(L87<>"",L87>0,P87<>""),P87/L87,"") | R87: =IF(AND(P87<>"",P87>0),(I87+J87+K87)/P87,"")
A88: 2026-01-10 | B88: 2周 | C88: 抖音 | F88: https://v.douyin.com/BnSsK5FXsMg/ | G88: 1225 | H88: 新年好物 | I88: 200 | K88: 55.5 | L88: 368000 | M88: 13000 | N88: 555 | O88: 139 | P88: =IF(AND(M88<>"",M88>0),M88+N88+O88,"") | Q88: =IF(AND(L88<>"",L88>0,P88<>""),P88/L88,"") | R88: =IF(AND(P88<>"",P88>0),(I88+J88+K88)/P88,"")
A89: 2026-01-10 | B89: 2周 | C89: 抖音 | F89: https://v.douyin.com/6PcuDigNKCQ/ | G89: 0001A1 | H89: 文严文 | K89: 107.5 | L89: 1400 | M89: 122 | N89: 2 | O89: 4 | P89: =IF(AND(M89<>"",M89>0),M89+N89+O89,"") | Q89: =IF(AND(L89<>"",L89>0,P89<>""),P89/L89,"") | R89: =IF(AND(P89<>"",P89>0),(I89+J89+K89)/P89,"")
A90: 2026-01-10 | B90: 2周 | C90: 抖音 | F90: https://v.douyin.com/M_OD5Un0s7g/ | G90: 0001A1 | H90: 文严文 | K90: 107.5 | L90: 903 | M90: 124 | N90: 4 | O90: 5 | P90: =IF(AND(M90<>"",M90>0),M90+N90+O90,"") | Q90: =IF(AND(L90<>"",L90>0,P90<>""),P90/L90,"") | R90: =IF(AND(P90<>"",P90>0),(I90+J90+K90)/P90,"")
A91: 2026-01-10 | B91: 2周 | C91: 抖音 | F91: https://v.douyin.com/RoY_ccBE9aE/ | G91: 0001A1 | H91: 文严文 | K91: 107.5 | L91: 5864 | M91: 445 | N91: 20 | O91: 25 | P91: =IF(AND(M91<>"",M91>0),M91+N91+O91,"") | Q91: =IF(AND(L91<>"",L91>0,P91<>""),P91/L91,"") | R91: =IF(AND(P91<>"",P91>0),(I91+J91+K91)/P91,"")
A92: 2026-01-10 | B92: 2周 | C92: 抖音 | F92: https://v.douyin.com/E43biAr3baM/ | G92: 1172W | H92: 李煜东 | K92: 57.5 | L92: 14000 | M92: 595 | N92: 36 | O92: 36 | P92: =IF(AND(M92<>"",M92>0),M92+N92+O92,"") | Q92: =IF(AND(L92<>"",L92>0,P92<>""),P92/L92,"") | R92: =IF(AND(P92<>"",P92>0),(I92+J92+K92)/P92,"")
A93: 2026-01-10 | B93: 2周 | C93: 抖音 | F93: https://v.douyin.com/lPzZG8Bvi_0/ | G93: 495 | H93: 穿搭 | K93: 93 | L93: 14000 | M93: 398 | N93: 10 | O93: 23 | P93: =IF(AND(M93<>"",M93>0),M93+N93+O93,"") | Q93: =IF(AND(L93<>"",L93>0,P93<>""),P93/L93,"") | R93: =IF(AND(P93<>"",P93>0),(I93+J93+K93)/P93,"")
A94: 2026-01-10 | B94: 2周 | C94: 小红书 | F94: https://www.xiaohongshu.com/discovery/item/6961ebdb00000000220237c3?xsec_token=CB3nu7tsqxMdDeXtMzhh5PG8g6Q3x3NLJ3n4qToJgm1EU=&xsec_source=app_share&type=video | G94: 495 | H94: 高桥大翔 | K94: 93 | L94: 440 | M94: 44 | N94: 5 | O94: 1 | P94: =IF(AND(M94<>"",M94>0),M94+N94+O94,"") | Q94: =IF(AND(L94<>"",L94>0,P94<>""),P94/L94,"") | R94: =IF(AND(P94<>"",P94>0),(I94+J94+K94)/P94,"")
A95: 2026-01-10 | B95: 2周 | C95: 小红书 | F95: https://www.xiaohongshu.com/discovery/item/6961ecd9000000001a035f7a?xsec_token=CBU2uhBjbYkl8OSJDZOwoYsMBjccypTh7RERQ1bVloyhU=&xsec_source=app_share&type=video | G95: 495 | H95: 穿搭 | I95: 100 | K95: 93 | L95: 5709 | M95: 420 | N95: 99 | O95: 16 | P95: =IF(AND(M95<>"",M95>0),M95+N95+O95,"") | Q95: =IF(AND(L95<>"",L95>0,P95<>""),P95/L95,"") | R95: =IF(AND(P95<>"",P95>0),(I95+J95+K95)/P95,"")
A96: 2026-01-10 | B96: 2周 | C96: 小红书 | F96: https://www.xiaohongshu.com/discovery/item/6962222d000000001a025ec9?xsec_token=CBcKOFMbB7Suc9TwwuaY-co2h8gOH_ZsHrgS1LmsGrKc8=&xsec_source=app_share&type=video | G96: 1225 | H96: 新年好物 | I96: 200 | K96: 55.5 | L96: 480 | M96: 67 | N96: 32 | O96: 52 | P96: =IF(AND(M96<>"",M96>0),M96+N96+O96,"") | Q96: =IF(AND(L96<>"",L96>0,P96<>""),P96/L96,"") | R96: =IF(AND(P96<>"",P96>0),(I96+J96+K96)/P96,"")
A97: 2026-01-11 | B97: 2周 | C97: 抖音 | F97: https://v.douyin.com/I8lYk8zIYh0/ | G97: 495 | H97: 穿搭 | K97: 93 | L97: 4000 | M97: 254 | N97: 9 | O97: 18 | P97: =IF(AND(M97<>"",M97>0),M97+N97+O97,"") | Q97: =IF(AND(L97<>"",L97>0,P97<>""),P97/L97,"") | R97: =IF(AND(P97<>"",P97>0),(I97+J97+K97)/P97,"")
A98: 2026-01-11 | B98: 2周 | C98: 抖音 | F98: https://v.douyin.com/-dkykCn_R8o/ U@l.pD | G98: 495 | H98: 口播 | I98: 150 | K98: 93 | L98: 5753 | M98: 167 | N98: 59 | O98: 39 | P98: =IF(AND(M98<>"",M98>0),M98+N98+O98,"") | Q98: =IF(AND(L98<>"",L98>0,P98<>""),P98/L98,"") | R98: =IF(AND(P98<>"",P98>0),(I98+J98+K98)/P98,"")
A99: 2026-01-11 | B99: 2周 | C99: 抖音 | F99: https://v.douyin.com/s6Tw4D3CZvs/ | G99: 1225 | H99: 新年好物 | K99: 55.5 | L99: 29000 | M99: 1298 | N99: 140 | O99: 122 | P99: =IF(AND(M99<>"",M99>0),M99+N99+O99,"") | Q99: =IF(AND(L99<>"",L99>0,P99<>""),P99/L99,"") | R99: =IF(AND(P99<>"",P99>0),(I99+J99+K99)/P99,"")
A100: 2026-01-11 | B100: 2周 | C100: 抖音 | F100: https://v.douyin.com/35xENcupcmY/ | G100: 0001A1 | H100: 新年好物 | I100: 70 | K100: 107.5 | L100: 18000 | M100: 376 | N100: 233 | O100: 12 | P100: =IF(AND(M100<>"",M100>0),M100+N100+O100,"") | Q100: =IF(AND(L100<>"",L100>0,P100<>""),P100/L100,"") | R100: =IF(AND(P100<>"",P100>0),(I100+J100+K100)/P100,"")
...

Sheet 达人主数据
A1: 达人ID | B1: 达人姓名 | C1: 所属平台 | D1: 粉丝量级 | E1: 达人分级 | F1: 签约状态 | G1: 所属机构 | H1: 联系方式 | I1: 合作类型 | J1: 首次合作日期 | K1: 累计合作次数 | L1: 累计投放费用 | M1: 平均互动率 | N1: 备注
A2: （暂无达人数据，后续做达人投放时在此添加）
A3: ↓ 公式示例（后续添加达人时参考） ↓
A4: 示例：KOL001 | B4: 示例达人 | K4: =IF(A4<>"",COUNTIF(投放明细表!D:D,A4),"") | L4: =IF(A4<>"",SUMIF(投放明细表!D:D,A4,投放明细表!I:I)+SUMIF(投放明细表!D:D,A4,投放明细表!J:J)+SUMIF(投放明细表!D:D,A4,投放明细表!K:K),"") | M4: =IF(A4<>"",IFERROR(AVERAGEIF(投放明细表!D:D,A4,投放明细表!Q:Q),""),"")

Sheet 款式主数据
A1: 款式编号 | B1: 款式名称 | C1: 品类 | D1: 成本价 | E1: 售价 | F1: 毛利率 | G1: 上市时间 | H1: 主推平台 | I1: 状态 | J1: 累计投放费用 | K1: 累计互动量 | L1: 备注
A2: 495 | C2: 鞋 | D2: 93 | F2: =IF(AND(D2<>"",E2<>"",E2>0),(E2-D2)/E2,"") | H2: 抖音 | I2: 在推 | J2: =IF(A2<>"",SUMIF(投放明细表!G:G,A2,投放明细表!I:I)+SUMIF(投放明细表!G:G,A2,投放明细表!J:J)+SUMIF(投放明细表!G:G,A2,投放明细表!K:K),"") | K2: =IF(A2<>"",SUMIF(投放明细表!G:G,A2,投放明细表!P:P),"")
A3: 0002A1 | C3: 鞋 | D3: 110.5 | F3: =IF(AND(D3<>"",E3<>"",E3>0),(E3-D3)/E3,"") | H3: 抖音 | I3: 在推 | J3: =IF(A3<>"",SUMIF(投放明细表!G:G,A3,投放明细表!I:I)+SUMIF(投放明细表!G:G,A3,投放明细表!J:J)+SUMIF(投放明细表!G:G,A3,投放明细表!K:K),"") | K3: =IF(A3<>"",SUMIF(投放明细表!G:G,A3,投放明细表!P:P),"")
A4: 0001A1 | C4: 鞋 | D4: 107.5 | F4: =IF(AND(D4<>"",E4<>"",E4>0),(E4-D4)/E4,"") | H4: 抖音 | I4: 在推 | J4: =IF(A4<>"",SUMIF(投放明细表!G:G,A4,投放明细表!I:I)+SUMIF(投放明细表!G:G,A4,投放明细表!J:J)+SUMIF(投放明细表!G:G,A4,投放明细表!K:K),"") | K4: =IF(A4<>"",SUMIF(投放明细表!G:G,A4,投放明细表!P:P),"")
A5: 459 | C5: 鞋 | D5: 46.5 | F5: =IF(AND(D5<>"",E5<>"",E5>0),(E5-D5)/E5,"") | H5: 抖音 | I5: 在推 | J5: =IF(A5<>"",SUMIF(投放明细表!G:G,A5,投放明细表!I:I)+SUMIF(投放明细表!G:G,A5,投放明细表!J:J)+SUMIF(投放明细表!G:G,A5,投放明细表!K:K),"") | K5: =IF(A5<>"",SUMIF(投放明细表!G:G,A5,投放明细表!P:P),"")
A6: 0003A2 | C6: 鞋 | D6: 49.5 | F6: =IF(AND(D6<>"",E6<>"",E6>0),(E6-D6)/E6,"") | H6: 抖音 | I6: 在推 | J6: =IF(A6<>"",SUMIF(投放明细表!G:G,A6,投放明细表!I:I)+SUMIF(投放明细表!G:G,A6,投放明细表!J:J)+SUMIF(投放明细表!G:G,A6,投放明细表!K:K),"") | K6: =IF(A6<>"",SUMIF(投放明细表!G:G,A6,投放明细表!P:P),"")
A7: 489 | C7: 鞋 | D7: 53.5 | F7: =IF(AND(D7<>"",E7<>"",E7>0),(E7-D7)/E7,"") | H7: 抖音 | I7: 在推 | J7: =IF(A7<>"",SUMIF(投放明细表!G:G,A7,投放明细表!I:I)+SUMIF(投放明细表!G:G,A7,投放明细表!J:J)+SUMIF(投放明细表!G:G,A7,投放明细表!K:K),"") | K7: =IF(A7<>"",SUMIF(投放明细表!G:G,A7,投放明细表!P:P),"")
A8: 001A1 | C8: 鞋 | D8: 107.5 | F8: =IF(AND(D8<>"",E8<>"",E8>0),(E8-D8)/E8,"") | H8: 抖音 | I8: 在推 | J8: =IF(A8<>"",SUMIF(投放明细表!G:G,A8,投放明细表!I:I)+SUMIF(投放明细表!G:G,A8,投放明细表!J:J)+SUMIF(投放明细表!G:G,A8,投放明细表!K:K),"") | K8: =IF(A8<>"",SUMIF(投放明细表!G:G,A8,投放明细表!P:P),"")
A9: 1093W | C9: 鞋 | F9: =IF(AND(D9<>"",E9<>"",E9>0),(E9-D9)/E9,"") | H9: 抖音 | I9: 在推 | J9: =IF(A9<>"",SUMIF(投放明细表!G:G,A9,投放明细表!I:I)+SUMIF(投放明细表!G:G,A9,投放明细表!J:J)+SUMIF(投放明细表!G:G,A9,投放明细表!K:K),"") | K9: =IF(A9<>"",SUMIF(投放明细表!G:G,A9,投放明细表!P:P),"")
A10: 1217W | C10: 鞋 | D10: 54 | F10: =IF(AND(D10<>"",E10<>"",E10>0),(E10-D10)/E10,"") | H10: 抖音 | I10: 在推 | J10: =IF(A10<>"",SUMIF(投放明细表!G:G,A10,投放明细表!I:I)+SUMIF(投放明细表!G:G,A10,投放明细表!J:J)+SUMIF(投放明细表!G:G,A10,投放明细表!K:K),"") | K10: =IF(A10<>"",SUMIF(投放明细表!G:G,A10,投放明细表!P:P),"")
A11: 1225 | C11: 鞋 | D11: 55.5 | F11: =IF(AND(D11<>"",E11<>"",E11>0),(E11-D11)/E11,"") | H11: 抖音 | I11: 在推 | J11: =IF(A11<>"",SUMIF(投放明细表!G:G,A11,投放明细表!I:I)+SUMIF(投放明细表!G:G,A11,投放明细表!J:J)+SUMIF(投放明细表!G:G,A11,投放明细表!K:K),"") | K11: =IF(A11<>"",SUMIF(投放明细表!G:G,A11,投放明细表!P:P),"")
A12: 492 | C12: 鞋 | D12: 69.5 | F12: =IF(AND(D12<>"",E12<>"",E12>0),(E12-D12)/E12,"") | H12: 抖音 | I12: 在推 | J12: =IF(A12<>"",SUMIF(投放明细表!G:G,A12,投放明细表!I:I)+SUMIF(投放明细表!G:G,A12,投放明细表!J:J)+SUMIF(投放明细表!G:G,A12,投放明细表!K:K),"") | K12: =IF(A12<>"",SUMIF(投放明细表!G:G,A12,投放明细表!P:P),"")
A13: 1172W | C13: 鞋 | D13: 57.5 | F13: =IF(AND(D13<>"",E13<>"",E13>0),(E13-D13)/E13,"") | H13: 抖音 | I13: 在推 | J13: =IF(A13<>"",SUMIF(投放明细表!G:G,A13,投放明细表!I:I)+SUMIF(投放明细表!G:G,A13,投放明细表!J:J)+SUMIF(投放明细表!G:G,A13,投放明细表!K:K),"") | K13: =IF(A13<>"",SUMIF(投放明细表!G:G,A13,投放明细表!P:P),"")
A14: 486 | C14: 鞋 | D14: 52.5 | F14: =IF(AND(D14<>"",E14<>"",E14>0),(E14-D14)/E14,"") | H14: 抖音 | I14: 测试 | J14: =IF(A14<>"",SUMIF(投放明细表!G:G,A14,投放明细表!I:I)+SUMIF(投放明细表!G:G,A14,投放明细表!J:J)+SUMIF(投放明细表!G:G,A14,投放明细表!K:K),"") | K14: =IF(A14<>"",SUMIF(投放明细表!G:G,A14,投放明细表!P:P),"")
A15: 000A1 | C15: 鞋 | D15: 107.5 | F15: =IF(AND(D15<>"",E15<>"",E15>0),(E15-D15)/E15,"") | H15: 抖音 | I15: 测试 | J15: =IF(A15<>"",SUMIF(投放明细表!G:G,A15,投放明细表!I:I)+SUMIF(投放明细表!G:G,A15,投放明细表!J:J)+SUMIF(投放明细表!G:G,A15,投放明细表!K:K),"") | K15: =IF(A15<>"",SUMIF(投放明细表!G:G,A15,投放明细表!P:P),"")
A16: 493AX | C16: 鞋 | D16: 98 | F16: =IF(AND(D16<>"",E16<>"",E16>0),(E16-D16)/E16,"") | H16: 抖音 | I16: 测试 | J16: =IF(A16<>"",SUMIF(投放明细表!G:G,A16,投放明细表!I:I)+SUMIF(投放明细表!G:G,A16,投放明细表!J:J)+SUMIF(投放明细表!G:G,A16,投放明细表!K:K),"") | K16: =IF(A16<>"",SUMIF(投放明细表!G:G,A16,投放明细表!P:P),"")
A17: 489Y | C17: 鞋 | D17: 53.5 | F17: =IF(AND(D17<>"",E17<>"",E17>0),(E17-D17)/E17,"") | H17: 抖音 | I17: 测试 | J17: =IF(A17<>"",SUMIF(投放明细表!G:G,A17,投放明细表!I:I)+SUMIF(投放明细表!G:G,A17,投放明细表!J:J)+SUMIF(投放明细表!G:G,A17,投放明细表!K:K),"") | K17: =IF(A17<>"",SUMIF(投放明细表!G:G,A17,投放明细表!P:P),"")
A18: 1227W | C18: 鞋 | D18: 61 | F18: =IF(AND(D18<>"",E18<>"",E18>0),(E18-D18)/E18,"") | H18: 小红书 | I18: 测试 | J18: =IF(A18<>"",SUMIF(投放明细表!G:G,A18,投放明细表!I:I)+SUMIF(投放明细表!G:G,A18,投放明细表!J:J)+SUMIF(投放明细表!G:G,A18,投放明细表!K:K),"") | K18: =IF(A18<>"",SUMIF(投放明细表!G:G,A18,投放明细表!P:P),"")
A19: 1225W | C19: 鞋 | D19: 60.5 | F19: =IF(AND(D19<>"",E19<>"",E19>0),(E19-D19)/E19,"") | H19: 抖音 | I19: 测试 | J19: =IF(A19<>"",SUMIF(投放明细表!G:G,A19,投放明细表!I:I)+SUMIF(投放明细表!G:G,A19,投放明细表!J:J)+SUMIF(投放明细表!G:G,A19,投放明细表!K:K),"") | K19: =IF(A19<>"",SUMIF(投放明细表!G:G,A19,投放明细表!P:P),"")

Sheet 更新指南
A1: 📋 达人投放数据 - 使用指南
A3: 一、文件结构
A4: 1. 投放明细表 - 每条投放记录一行（1-7月历史数据已填充）
A5: 2. 达人主数据 - 目前暂无达人维度数据，后续做达人投放时在此维护
A6: 3. 款式主数据 - 18个款式，累计数据自动联动更新
A7: 4. 更新指南 - 本页
A9: 二、字段映射说明（原始数据 → 新模板）
A10: 日期 → 投放日期
A11: （计算）→ 所属周（根据日期自动算出第几周）
A12: 平台 → 平台
A13: （暂无）→ 达人ID / 达人姓名（留空）
A14: 发布链接 → 内容链接
... A31: 款式主数据的累计值会自动更新
